{
  "id": "20260609-take-your-local-github-sessions-anywhere-585af7b0",
  "title": "案例复盘：GitHub 的案例线索",
  "original_title": "Take your local GitHub sessions anywhere",
  "url": "https://github.blog/news-insights/product-news/take-your-local-github-sessions-anywhere/",
  "summary": "Kick off work in VS Code or the CLI, finish it from your phone. Remote control for GitHub Copilot sessions is now generally available on github.com and GitHub Mobile. The post Take your local GitHub sessions anywhere appeared first on The GitHub Blog .",
  "source_category": "ai_tools",
  "source_category_title": "AI 工具与开发者平台",
  "source_name": "The latest on AI & ML - The GitHub Blog",
  "source_type": "rss",
  "feed_url": "https://github.blog/ai-and-ml/feed/",
  "published_at": "2026-05-18T16:54:53+00:00",
  "fetched_at": "2026-06-09T03:37:17.192336+00:00",
  "decision": "brief",
  "report_type": "case-study",
  "report_type_title": "案例复盘",
  "score": 45,
  "reader_hook": "这条线索有具体项目或案例，可以拆哪些条件可复制，哪些只是别人自己的局。",
  "why_now": "来自本批次稳定公开源，适合先进入 Radar 观察。",
  "evidence_level": "official",
  "reason": "命中老花主线关键词，且来源可复查。",
  "collection_fit": "部分符合收集原则：可以进入简报观察，但证据链或读者入口还不够完整。",
  "investigation_direction": "优先追项目原始页面、代码仓库、作者复盘、收入/增长证据和不可复制条件。",
  "uncertainty_flags": [
    "尚未抓取正文外的补充证据。",
    "尚未形成多源交叉验证。",
    "当前仅适合简报观察，不宜写成深度结论。"
  ],
  "facts": [
    {
      "claim": "The latest on AI & ML - The GitHub Blog 发布/收录了这条原始线索：Take your local GitHub sessions anywhere",
      "type": "confirmed_fact",
      "source_url": "https://github.blog/news-insights/product-news/take-your-local-github-sessions-anywhere/",
      "confidence": 0.8
    }
  ],
  "sources": [
    {
      "title": "The latest on AI & ML - The GitHub Blog",
      "url": "https://github.blog/news-insights/product-news/take-your-local-github-sessions-anywhere/",
      "source_type": "official",
      "used_for": "原始线索和事实入口"
    }
  ],
  "traceability": {
    "matched_keywords": {
      "ai": [
        "ai",
        "copilot"
      ],
      "dev": [
        "github"
      ]
    },
    "source_host": "github.blog",
    "source_type": "rss",
    "heuristic": true
  },
  "verification": {
    "what_is_confirmed": [
      "标题、来源 URL、来源类型、抓取时间已记录。",
      "该条线索来自稳定公开源，而不是强反爬论坛或截图转述。"
    ],
    "what_needs_followup": [
      "继续追官方文档、价格页、GitHub 仓库、真实用户案例或反方证据。",
      "确认成本、门槛、合规、平台规则或岗位影响的具体边界。",
      "把所有无证据、弱证据和推断点显式标记，等待补证后再升级结论。"
    ],
    "expert_challenge_points": [
      "不能把单条线索写成已验证机会。",
      "不能把技术可实现直接推导为商业可赚钱。",
      "涉及价格、收益、比例时必须继续找来源或公式。"
    ],
    "do_not_claim": [
      "不要声称老花已经实操验证。",
      "不要声称普通人都能复制。",
      "不要在证据不足时给完整行动方案。"
    ]
  },
  "persona_connection": {
    "line": "程序员技术视角下的信息差、成本、平台规则和副业机会判断。",
    "why_it_matters": "这条线索有具体项目或案例，可以拆哪些条件可复制，哪些只是别人自己的局。",
    "fit_for_radar": false
  }
}
